MANIFEST.in
requirements.txt
setup.py
vialink/utils/background_task/__init__.py
vialink/utils/background_task/abstract.py
vialink/utils/background_task/clock.py
vialink/utils/background_task/constant.py
vialink/utils/background_task/executor.py
vialink/utils/background_task/launcher.py
vialink/utils/background_task/parameter_storage.py
vialink/utils/background_task/repository.py
vialink/utils/background_task/settings.py
vialink/utils/background_task/status_storage.py
vialink/utils/background_task/task.py
vialink/utils/background_task/factory/__init__.py
vialink/utils/background_task/factory/parameter_storage.py
vialink/utils/background_task/factory/repository.py
vialink/utils/background_task/factory/status_storage.py
vialink/utils/background_task/infrastructure/__init__.py
vialink/utils/background_task/infrastructure/dynamo.py
vialink/utils/background_task/infrastructure/s3.py
vialink_utils_mongo_background_task.egg-info/PKG-INFO
vialink_utils_mongo_background_task.egg-info/SOURCES.txt
vialink_utils_mongo_background_task.egg-info/dependency_links.txt
vialink_utils_mongo_background_task.egg-info/requires.txt
vialink_utils_mongo_background_task.egg-info/top_level.txt